[{
    "linkName": {
        "en-US": "Home",
        "zh-Hant-TW": "首頁"
    },
    "linkIcon": "home",
    "href": "index.html"
}, {
    "linkName": {
        "en-US": "Articles",
        "zh-Hant-TW": "文章"
    },
    "linkIcon": "article",
    "href": "article.html"
}, {
    "linkName": {
        "en-US": "About",
        "zh-Hant-TW": "關於"
    },
    "linkIcon": "account_circle",
    "href": "about.html"
}, {
    "linkName": {
        "en-US": "Settings",
        "zh-Hant-TW": "設定"
    },
    "linkIcon": "settings",
    "href": "#settings"
}]